{
  "single_source": {
    "kind": "git",
    "ref": "0444b6d2f796ce55c9e14231430eac9f7e0b27ca",
    "git": "git@github.com:mesosphere/mesos.git",
    "ref_origin": "pkg-builder/mesos-4b6269c1"
  },
  "environment": {
    "MESOS_NATIVE_JAVA_LIBRARY": "/opt/mesosphere/lib/libmesos.so",
    "JAVA_LIBRARY_PATH": "/opt/mesosphere/lib"
  },
  "requires": [
    "openssl",
    "libevent",
    "curl",
    "boost-libs"
  ],
  "sysctl": {
    "dcos-mesos-slave-public": {
      "vm.max_map_count": 262144,
      "vm.swappiness": 1
    },
    "dcos-mesos-slave": {
      "vm.max_map_count": 262144,
      "vm.swappiness": 1
    }
  },
  "state_directory": true
}