{
  "sysctl": {
    "dcos-mesos-slave-public": {
      "vm.max_map_count": 262144,
      "vm.swappiness": 1
    },
    "dcos-mesos-slave": {
      "vm.max_map_count": 262144,
      "vm.swappiness": 1
    }
  },
  "single_source": {
    "ref": "1ede9c5dc0993cefd502090b7cbfbd8afc3df21b",
    "git": "git@github.com:mesosphere/mesos.git",
    "ref_origin": "pkg-builder/mesos-09efd575",
    "kind": "git"
  },
  "requires": [
    "openssl",
    "libevent",
    "curl",
    "boost-libs"
  ],
  "environment": {
    "JAVA_LIBRARY_PATH": "/opt/mesosphere/lib",
    "MESOS_NATIVE_JAVA_LIBRARY": "/opt/mesosphere/lib/libmesos.so"
  },
  "state_directory": true
}