{
  "requires": [
    "openssl",
    "libevent",
    "curl",
    "boost-libs"
  ],
  "single_source": {
    "ref": "ed91bd1b7b2aa9fd69cb83f4f5bb80e46493dfcc",
    "git": "git@github.com:mesosphere/mesos.git",
    "kind": "git",
    "ref_origin": "pkg-builder/mesos-4f165357"
  },
  "state_directory": true,
  "environment": {
    "JAVA_LIBRARY_PATH": "/opt/mesosphere/lib",
    "MESOS_NATIVE_JAVA_LIBRARY": "/opt/mesosphere/lib/libmesos.so"
  },
  "sysctl": {
    "dcos-mesos-slave-public": {
      "vm.max_map_count": 262144,
      "vm.swappiness": 1
    },
    "dcos-mesos-slave": {
      "vm.max_map_count": 262144,
      "vm.swappiness": 1
    }
  }
}