{
  "state_directory": true,
  "requires": [
    "openssl",
    "libevent",
    "curl",
    "boost-libs"
  ],
  "environment": {
    "MESOS_NATIVE_JAVA_LIBRARY": "/opt/mesosphere/lib/libmesos.so",
    "JAVA_LIBRARY_PATH": "/opt/mesosphere/lib"
  },
  "single_source": {
    "ref": "a249aee7c163641efb8d6112f04ffe6d407c6ce3",
    "ref_origin": "pkg-builder/mesos-7b1ab032",
    "git": "git@github.com:mesosphere/mesos.git",
    "kind": "git"
  },
  "sysctl": {
    "dcos-mesos-slave-public": {
      "vm.swappiness": 1,
      "vm.max_map_count": 262144
    },
    "dcos-mesos-slave": {
      "vm.swappiness": 1,
      "vm.max_map_count": 262144
    }
  }
}