{
  "requires": [
    "openssl",
    "libevent",
    "curl",
    "boost-libs"
  ],
  "sysctl": {
    "dcos-mesos-slave-public": {
      "vm.swappiness": 1,
      "vm.max_map_count": 262144
    },
    "dcos-mesos-slave": {
      "vm.swappiness": 1,
      "vm.max_map_count": 262144
    }
  },
  "environment": {
    "JAVA_LIBRARY_PATH": "/opt/mesosphere/lib",
    "MESOS_NATIVE_JAVA_LIBRARY": "/opt/mesosphere/lib/libmesos.so"
  },
  "single_source": {
    "kind": "git",
    "git": "git@github.com:mesosphere/mesos.git",
    "ref": "45ed8ca2a9e31acd7ed78d117d30ea8757b31269",
    "ref_origin": "pkg-builder/mesos-0303b8d2"
  },
  "state_directory": true
}