{
  "sysctl": {
    "dcos-mesos-slave": {
      "vm.swappiness": 1,
      "vm.max_map_count": 262144
    },
    "dcos-mesos-slave-public": {
      "vm.swappiness": 1,
      "vm.max_map_count": 262144
    }
  },
  "requires": [
    "openssl",
    "libevent",
    "curl",
    "boost-libs"
  ],
  "state_directory": true,
  "environment": {
    "MESOS_NATIVE_JAVA_LIBRARY": "/opt/mesosphere/lib/libmesos.so",
    "JAVA_LIBRARY_PATH": "/opt/mesosphere/lib"
  },
  "single_source": {
    "git": "git@github.com:mesosphere/mesos.git",
    "kind": "git",
    "ref_origin": "pkg-builder/mesos-ae24a4bf",
    "ref": "32cee6a27573d1e1b0f5b8c8691b81296711909e"
  }
}